popbl_chassis/__init__.py
popbl_chassis/utils.py
popbl_chassis/database/__init__.py
popbl_chassis/database/db_utils.py
popbl_chassis/discovery/__init__.py
popbl_chassis/discovery/consulprovider.py
popbl_chassis/errormanager/__init__.py
popbl_chassis/errormanager/circuitbreaker.py
popbl_chassis/logger/__init__.py
popbl_chassis/logger/loglevel.py
popbl_chassis/logger/lokilogger.py
popbl_chassis/logger/jsonformatter/__init__.py
popbl_chassis/logger/jsonformatter/logdataformatter.py
popbl_chassis/logger/jsonformatter/requestdataformatter.py
popbl_chassis/messaging/__init__.py
popbl_chassis/messaging/eventprovider.py
popbl_chassis/messaging/loggerprovider.py
popbl_chassis/messaging/lokiloggerprovider.py
popbl_chassis/security/__init__.py
popbl_chassis/security/middleware.py
popbl_chassis/security/securityprovider.py
team3_pobl_chassis-2.0.18.dist-info/METADATA
team3_pobl_chassis-2.0.18.dist-info/WHEEL
team3_pobl_chassis-2.0.18.dist-info/top_level.txt
team3_pobl_chassis-2.0.18.dist-info/RECORD
