Metadata-Version: 2.1
Name: team3_pobl_chassis
Version: 2.0.18
Summary: A reusable library for microservices
Author: macc-team3
Author-email: gorka.etxebarria@alumni.mondragon.edu
